django_dbpool/__init__.py
django_dbpool/db/__init__.py
django_dbpool/db/backends/__init__.py
django_dbpool/db/backends/postgis/__init__.py
django_dbpool/db/backends/postgis/base.py
django_dbpool/db/backends/postgresql_psycopg2/__init__.py
django_dbpool/db/backends/postgresql_psycopg2/base.py
django_dbpool-0.1.0.dist-info/METADATA
django_dbpool-0.1.0.dist-info/RECORD
django_dbpool-0.1.0.dist-info/WHEEL
django_dbpool-0.1.0.dist-info/top_level.txt
