Metadata-Version: 2.1
Name: django-dbpool
Version: 0.1.0
Summary: Postgresql + PostGIS Connection Pooling for Django.
Home-page: https://github.com/chrysls/django-dbpool
Author: UNKNOWN
Author-email: UNKNOWN
License: MIT
Platform: UNKNOWN
Classifier: Intended Audience :: Developers
Classifier: Natural Language :: English
Classifier: License :: OSI Approved :: MIT License
Classifier: Programming Language :: Python
Classifier: Framework :: Django
Classifier: Programming Language :: Python :: 3
Requires-Dist: psycopg2
Requires-Dist: sqlalchemy
